pyenopt_sqlite/__init__.py
pyenopt_sqlite/batch.py
pyenopt_sqlite/calculation_result.py
pyenopt_sqlite/control_definition.py
pyenopt_sqlite/control_value.py
pyenopt_sqlite/database.py
pyenopt_sqlite/exceptions.py
pyenopt_sqlite/experiment.py
pyenopt_sqlite/function.py
pyenopt_sqlite/gradient_result.py
pyenopt_sqlite/py.typed
pyenopt_sqlite/realization.py
pyenopt_sqlite/simulation.py
pyenopt_sqlite/simulation_result.py
pyenopt_sqlite/snapshot.py
pyenopt_sqlite/sqlite_storage.py
pyenopt_sqlite/version.py
pyenopt-0.0.1.dist-info/LICENSE
pyenopt-0.0.1.dist-info/METADATA
pyenopt-0.0.1.dist-info/WHEEL
pyenopt-0.0.1.dist-info/top_level.txt
pyenopt-0.0.1.dist-info/RECORD
